blockscope.py
blockscope-0.1.3.dist-info/LICENSE
blockscope-0.1.3.dist-info/WHEEL
blockscope-0.1.3.dist-info/METADATA
blockscope-0.1.3.dist-info/RECORD
