Metadata-Version: 2.1
Name: blockscope
Version: 0.1.3
Summary: Utility for local block scoped variables 
Author-email: Anton Petersen <quarkatron@gmail.com>
Requires-Python: >=3.5
Classifier: License :: OSI Approved :: MIT License
Project-URL: Home, https://github.com/anptrs/blockscope
